lamar_folder_sync/__init__.py
lamar_folder_sync/cli.py
lamar_folder_sync/config.py
lamar_folder_sync/sync.py
lamar_folder_sync-1.0.0.dist-info/METADATA
lamar_folder_sync-1.0.0.dist-info/WHEEL
lamar_folder_sync-1.0.0.dist-info/entry_points.txt
lamar_folder_sync-1.0.0.dist-info/top_level.txt
lamar_folder_sync-1.0.0.dist-info/RECORD
