Metadata-Version: 2.1
Name: lamar-folder-sync
Version: 1.0.0
Summary: A Python package to replicate folders in Lamar CMS.
Home-page: 
Author: Your Name
Author-email: your.email@example.com
Classifier: Programming Language :: Python :: 3
Classifier: License :: OSI Approved :: MIT License
Classifier: Operating System :: OS Independent
Requires-Python: >=3.7
Requires-Dist: requests
Requires-Dist: python-dotenv
